nonebot_plugin_trpglogger/__init__.py
nonebot_plugin_trpglogger/data.py
nonebot_plugin_trpglogger/handle.py
nonebot_plugin_trpglogger/upload.py
nonebot_plugin_trpglogger-0.4.2.dist-info/WHEEL
nonebot_plugin_trpglogger-0.4.2.dist-info/METADATA
nonebot_plugin_trpglogger-0.4.2.dist-info/licenses/LICENSE
nonebot_plugin_trpglogger-0.4.2.dist-info/RECORD
