Metadata-Version: 2.1
Name: nonebot_plugin_trpglogger
Version: 0.4.2
Summary: a logger for TRPG
License: AGPL-3.0
Author-email: Jigsaw <j1g5aw@foxmail.com>
Requires-Python: >=3.8,<4.0
Requires-Dist: aiofiles<1.0.0,>=0.8.0
Requires-Dist: httpx<1.0.0,>=0.23.1
Requires-Dist: nonebot-adapter-onebot<3.0.0,>=2.2.2
Requires-Dist: nonebot2<3.0.0,>=2.0.0
Project-URL: homepage, https://github.com/thereisnodice/TRPGLogger
Project-URL: repository, https://github.com/thereisnodice/TRPGLogger
